liteshort/__init__.py
liteshort/config.py
liteshort/config.template.yml
liteshort/liteshort.py
liteshort/util.py
liteshort/wsgi.py
liteshort/static/GitHub.svg
liteshort/static/favicon.ico
liteshort/static/styles.css
liteshort/templates/main.html
liteshort-1.3.0.dist-info/LICENSE
liteshort-1.3.0.dist-info/METADATA
liteshort-1.3.0.dist-info/WHEEL
liteshort-1.3.0.dist-info/entry_points.txt
liteshort-1.3.0.dist-info/top_level.txt
liteshort-1.3.0.dist-info/RECORD
