Metadata-Version: 2.1
Name: liteshort
Version: 1.3.0
Summary: User-friendly, actually lightweight, and configurable URL shortener
Author-email: Rose Spangler <rose@ikl.sh>
License: MIT
Classifier: Programming Language :: Python :: 3
Classifier: License :: OSI Approved :: MIT License
Classifier: Operating System :: POSIX :: Linux
Requires-Python: >=3.8
License-File: LICENSE
Requires-Dist: appdirs (~=1.4)
Requires-Dist: bcrypt (~=4.0)
Requires-Dist: flask (~=2.2)
Requires-Dist: pyyaml (~=6.0)
Requires-Dist: requests (~=2.28)
